steer_core/__init__.py
steer_core/Constants/Units.py
steer_core/Constants/Universal.py
steer_core/Constants/__init__.py
steer_core/ContextManagers/ContextManagers.py
steer_core/ContextManagers/__init__.py
steer_core/Data/DataManager.py
steer_core/Data/__init__.py
steer_core/Decorators/Coordinates.py
steer_core/Decorators/General.py
steer_core/Decorators/Objects.py
steer_core/Decorators/__init__.py
steer_core/Mixins/Colors.py
steer_core/Mixins/Coordinates.py
steer_core/Mixins/Data.py
steer_core/Mixins/Dunder.py
steer_core/Mixins/Plotter.py
steer_core/Mixins/Serializer.py
steer_core/Mixins/TypeChecker.py
steer_core/Mixins/__init__.py
steer_core-0.1.32.dist-info/METADATA
steer_core-0.1.32.dist-info/WHEEL
steer_core-0.1.32.dist-info/top_level.txt
steer_core-0.1.32.dist-info/RECORD
