Metadata-Version: 2.4
Name: steer-core
Version: 0.1.32
Summary: Modelling energy storage from cell to site - STEER OpenCell Design
Author-email: Nicholas Siemons <nsiemons@stanford.edu>
Maintainer-email: Nicholas Siemons <nsiemons@stanford.edu>
License: MIT
Project-URL: Homepage, https://github.com/nicholas9182/steer-core/
Project-URL: Repository, https://github.com/nicholas9182/steer-core/
Project-URL: Issues, https://github.com/nicholas9182/steer-core/issues
Project-URL: Documentation, https://github.com/nicholas9182/steer-core/
Keywords: energy,storage,battery,modeling,simulation
Classifier: Development Status :: 4 - Beta
Classifier: Programming Language :: Python :: 3
Classifier: Programming Language :: Python :: 3.10
Classifier: Programming Language :: Python :: 3.11
Classifier: Programming Language :: Python :: 3.12
Classifier: License :: OSI Approved :: MIT License
Classifier: Operating System :: OS Independent
Classifier: Topic :: Scientific/Engineering
Classifier: Topic :: Scientific/Engineering :: Physics
Requires-Python: >=3.10
Requires-Dist: pandas==2.1.4
Requires-Dist: numpy==1.26.4
Requires-Dist: datetime==5.5
Requires-Dist: plotly==6.2.0
Requires-Dist: scipy==1.15.3
Provides-Extra: dev
Requires-Dist: pytest>=7.0; extra == "dev"
Requires-Dist: pytest-cov; extra == "dev"
Requires-Dist: black; extra == "dev"
Requires-Dist: flake8; extra == "dev"
Requires-Dist: mypy; extra == "dev"
Requires-Dist: isort; extra == "dev"
Provides-Extra: test
Requires-Dist: pytest>=7.0; extra == "test"
Requires-Dist: pytest-cov; extra == "test"
